hopsparser/__init__.py
hopsparser/deptree.py
hopsparser/evaluator.py
hopsparser/lexers.py
hopsparser/main.py
hopsparser/mst.py
hopsparser/parser.py
hopsparser/server.py
hopsparser/spacy_component.py
hopsparser/utils.py
hopsparser/traintools/__init__.py
hopsparser/traintools/trainer.py
hopsparser-0.8.0.dist-info/licenses/LICENCE.md
hopsparser-0.8.0.dist-info/METADATA
hopsparser-0.8.0.dist-info/WHEEL
hopsparser-0.8.0.dist-info/entry_points.txt
hopsparser-0.8.0.dist-info/top_level.txt
hopsparser-0.8.0.dist-info/RECORD
