Metadata-Version: 2.4
Name: hopsparser
Version: 0.8.0
Summary: A graph dependency parser to tinker with
Author-email: Benoît Crabbé <benoit.crabbe@univ-paris-diderot.fr>, Loïc Grobol <lgrobol@parisnanterre.fr>
License-Expression: MIT
Project-URL: Bug Tracker, https://github.com/hopsparser/hopsparser/issues
Project-URL: Changes, https://github.com/hopsparser/hopsparser/blob/main/CHANGELOG.md
Project-URL: Documentation, https://hopsparser.readthedocs.io
Project-URL: Source Code, https://github.com/hopsparser/hopsparser
Keywords: nlp,parsing
Requires-Python: >=3.11
License-File: LICENCE.md
Requires-Dist: bidict
Requires-Dist: boltons
Requires-Dist: click<9.0.0,>=8.0.4
Requires-Dist: fastapi
Requires-Dist: fasttextlt
Requires-Dist: huggingface-hub
Requires-Dist: loguru
Requires-Dist: numpy>=2.1
Requires-Dist: pooch
Requires-Dist: pydantic<2.12,>=2.0
Requires-Dist: pydantic-settings<2.10,>=2.0
Requires-Dist: pyyaml
Requires-Dist: rich
Requires-Dist: sacremoses
Requires-Dist: tabulate2
Requires-Dist: torch<2.8.0,>=2.0.0
Requires-Dist: transformers!=4.23.0,!=4.23.1,!=4.51.0,<5.0.0,>=4.19.0
Requires-Dist: uvicorn
Provides-Extra: ci
Requires-Dist: pytest-github-actions-annotate-failures; extra == "ci"
Provides-Extra: spacy
Requires-Dist: spacy<4.0,>=3.8; extra == "spacy"
Provides-Extra: tests
Requires-Dist: hypothesis<7.0,>=6.0; extra == "tests"
Requires-Dist: networkx<3.5,>=3.2; extra == "tests"
Requires-Dist: pytest<9.0,>=7.0; extra == "tests"
Requires-Dist: pytest-assert-utils; extra == "tests"
Requires-Dist: pytest-console-scripts<1.5,>=1.4; extra == "tests"
Requires-Dist: pytest-github-actions-annotate-failures; extra == "tests"
Requires-Dist: pytest-lazy-fixtures<2,>=1.1; extra == "tests"
Provides-Extra: traintools
Requires-Dist: httpx[http2]; extra == "traintools"
Requires-Dist: lightning; extra == "traintools"
Requires-Dist: polars<1.30,>=1.12; extra == "traintools"
Requires-Dist: pytorch-lightning<3.0,>=2.4; extra == "traintools"
Requires-Dist: tensorboardx; extra == "traintools"
Requires-Dist: torchmetrics; extra == "traintools"
Dynamic: license-file
